numpynet/__init__.py
numpynet/activations.py
numpynet/callbacks.py
numpynet/exceptions.py
numpynet/initializers.py
numpynet/losses.py
numpynet/metrics.py
numpynet/network.py
numpynet/layers/__init__.py
numpynet/layers/activation.py
numpynet/layers/base.py
numpynet/layers/bias.py
numpynet/layers/conv.py
numpynet/layers/dense.py
numpynet/layers/dropout.py
numpynet/layers/flatten.py
numpynet/layers/input.py
numpynet/layers/pool.py
numpynet/layers/resize.py
numpynet/layers/softmax.py
numpynet/utils/__init__.py
numpynet/utils/convolution.py
numpynet/utils/shortcuts.py
numpynet/utils/statistics.py
numpynet-0.1.0.dist-info/LICENSE
numpynet-0.1.0.dist-info/METADATA
numpynet-0.1.0.dist-info/WHEEL
numpynet-0.1.0.dist-info/top_level.txt
numpynet-0.1.0.dist-info/zip-safe
numpynet-0.1.0.dist-info/RECORD
