Metadata-Version: 2.1
Name: numpynet
Version: 0.1.0
Summary: Simple neural network implementation with numpy
Home-page: https://github.com/klima7/CNN-From-Scratch
Author: Łukasz Klimkiewicz
Author-email: pypi@mail.ukasz.com
License: MIT
Keywords: neural,network,numpy,simple,convolution,dense
Classifier: Programming Language :: Python :: 3
License-File: LICENSE
Requires-Dist: numpy
Requires-Dist: scipy
Requires-Dist: scikit-learn
Requires-Dist: tqdm
Requires-Dist: numba
